peoplehealtimage/__init__.py
peoplehealtimage/pacote.py
peoplehealtimage-0.0.4.dist-info/LICENSE
peoplehealtimage-0.0.4.dist-info/METADATA
peoplehealtimage-0.0.4.dist-info/WHEEL
peoplehealtimage-0.0.4.dist-info/top_level.txt
peoplehealtimage-0.0.4.dist-info/RECORD
