Metadata-Version: 2.1
Name: peoplehealtimage
Version: 0.0.4
Summary: Detecção de faces em imagens
Author: Luis Eduardo
Author-email: duardos36@gmail.com
Classifier: Development Status :: 3 - Alpha
Classifier: Intended Audience :: Developers
Classifier: License :: OSI Approved :: MIT License
Classifier: Programming Language :: Python :: 3
Classifier: Programming Language :: Python :: 3.8
Classifier: Programming Language :: Python :: 3.9
Classifier: Programming Language :: Python :: 3.10
License-File: LICENSE
Requires-Dist: opencv-python
Requires-Dist: os
